pylix/__init__.py
pylix/algebra/__init__.py
pylix/algebra/equations.py
pylix/algebra/matrix.py
pylix/algebra/statics.py
pylix/algebra/vector.py
pylix/errors/__init__.py
pylix/errors/assertion.py
pylix/errors/decorator.py
pylix/errors/enums.py
pylix/errors/error_messages.py
pylix/errors/useful_errors.py
pylix/types.py
pylix-0.1.6.dist-info/LICENSE.md
pylix-0.1.6.dist-info/METADATA
pylix-0.1.6.dist-info/WHEEL
pylix-0.1.6.dist-info/RECORD
