Metadata-Version: 2.3
Name: pylix
Version: 0.1.6
Summary: Useful things for python
License: MIT
Author: SirMrManuel0
Requires-Python: >=3.12,<4.0
Classifier: License :: OSI Approved :: MIT License
Classifier: Programming Language :: Python :: 3
Classifier: Programming Language :: Python :: 3.12
Classifier: Programming Language :: Python :: 3.13
Requires-Dist: numpy (>=2.2.4,<3.0.0)
